Metadata-Version: 1.0
Name: lmign-dist
Version: 1.6
Summary: Gaussian distributions
Home-page: UNKNOWN
Author: UNKNOWN
Author-email: UNKNOWN
License: UNKNOWN
Platform: UNKNOWN
